MASTUDMSGUI/GUI_exportated_flies_extractor.py
MASTUDMSGUI/Updated_for_real_data_GUI_plotter.py
MASTUDMSGUI/__init__.py
MASTUDMSGUI/df_manipulation.py
MAST_U_DMS_GUI-0.1.17.dist-info/METADATA
MAST_U_DMS_GUI-0.1.17.dist-info/WHEEL
MAST_U_DMS_GUI-0.1.17.dist-info/entry_points.txt
MAST_U_DMS_GUI-0.1.17.dist-info/top_level.txt
MAST_U_DMS_GUI-0.1.17.dist-info/RECORD
