Metadata-Version: 2.1
Name: MAST-U-DMS-GUI
Version: 0.1.17
Summary: A GUI for spectral data analysis at MAST-U
Home-page: UNKNOWN
Author: Gareth Williams
Author-email: gw878@york.ac.uk
License: UNKNOWN
Platform: UNKNOWN
Requires-Python: >=3.0
Requires-Dist: Click
Requires-Dist: matplotlib (>=3.3.4)
Requires-Dist: pandas (>=1.2.3)
Requires-Dist: spe2py (>=2.0.0)
Requires-Dist: numpy (>=1.20.1)
Requires-Dist: scipy (>=1.6.1)
